{
  "jd_id": "ml_engineer_0049",
  "target_role_id": "ml_engineer",
  "target_role_name": "Machine Learning Engineer",
  "job_title": "Machine Learning Engineer",
  "company": "Pearson and Sons",
  "industry": "data_analytics",
  "seniority_band": "mid",
  "min_years_experience": 2,
  "required_skills": [
    "feature_stores",
    "docker_k8s",
    "python",
    "aws",
    "supervised_learning",
    "mlops",
    "sql"
  ],
  "required_skill_names": [
    "Feature Stores",
    "Docker & Kubernetes",
    "Python",
    "AWS",
    "Supervised Learning",
    "MLOps",
    "SQL"
  ],
  "preferred_skills": [
    "deep_learning"
  ],
  "preferred_skill_names": [
    "Deep Learning"
  ],
  "generated_at": "2026-07-20T16:51:35Z",
  "source": "synthetic_jd_generator",
  "license": "CC0-1.0 (synthetic; no real PII)"
}